{
  "MAP_SIZE": 11,
  "bgm": "https://res.cloudinary.com/dmdpjf8up/video/upload/v1764384182/into_the_graveyard_qwovim.mp3",

  "groundMap": [
    "###########",
    "###########",
    "###########",
    "###########",
    "###########",
    "###########",
    "###########",
    "###########",
    "###########",
    "###########",
    "###########"
  ],

  "ceilingMap": [
    "###########",
    "###########",
    "###########",
    "###########",
    "###########",
    "###########",
    "###########",
    "###########",
    "###########",
    "###########",
    "###########"
  ],

  "wallMap": [
    "###########",
    "###########",
    "##.......##",
    "##.......##",
    "##..#G#..##",
    "##..G#G..##",
    "##..#G#..##",
    "##.......##",
    "##.......##",
    "####T.T####",
    "#####D#####"
  ],

  "objectMap": [
    "...........",
    "...........",
    ".....P.....",
    "...........",
    "...........",
    "...........",
    "...........",
    "...........",
    "...........",
    "...........",
    "..........."
  ],

  "lightMap": [
    "...........",
    ".....B.....",
    "...........",
    "...........",
    "...........",
    ".B.......B.",
    "...........",
    "...........",
    "..G.....R..",
    ".....B.....",
    "..........."
  ],

  "portalMap": [
    "...........",
    "...........",
    "...........",
    "...........",
    "...........",
    "...........",
    "...........",
    "...........",
    "...........",
    ".....S.....",
    "..........."
  ],

  "structureMap": [
    "...........",
    "...........",
    "...........",
    "...........",
    "...........",
    "...........",
    "...........",
    "...........",
    "..B.....A..",
    "...........",
    "..........."
  ],

  "portals": {
    "S": {
      "url": "https://termcic.github.io/insect_ecology/rest_room.json",
      "spawn": { "i": 2, "j": 5 }
    }
  },

  "structures": {
    "A": {
      "url": "https://res.cloudinary.com/dmdpjf8up/image/upload/v1764534707/goddess_statue_3d_model_compressed_vjcwwn.glb",
      "scale": 3,
      "y": 0.0,
      "rotationY": 90
    },
    "B": {
      "url": "https://res.cloudinary.com/dmdpjf8up/image/upload/v1764543770/classical_statue_3d_model_compressed_g3n7gs.glb",
      "scale": 3,
      "y": 0.0,
      "rotationY": 45
    }
  }
}
